chacc/README.md
chacc/__init__.py
chacc/chacc.py
chacc/cli.py
chacc/demo_cache_structure.py
chacc/demo_module_separation.py
chacc/manager.py
chacc/utils.py
chacc_dependency_manager-1.1.1.dist-info/licenses/LICENSE
chacc_dependency_manager-1.1.1.dist-info/METADATA
chacc_dependency_manager-1.1.1.dist-info/WHEEL
chacc_dependency_manager-1.1.1.dist-info/entry_points.txt
chacc_dependency_manager-1.1.1.dist-info/top_level.txt
chacc_dependency_manager-1.1.1.dist-info/RECORD
