Metadata-Version: 2.4
Name: chacc-dependency-manager
Version: 1.1.1
Summary: Pip accelerator package. Intelligent, incremental dependency resolution and caching for pip environment based applications. It it meant to complement pip
Author-email: Jonas G Mwambimbi <jonasgeorge1015@gmail.com>
License: MIT
Project-URL: Homepage, https://github.com/Jonas1015/chacc-dependency-manager
Project-URL: Repository, https://github.com/Jonas1015/chacc-dependency-manager
Project-URL: Documentation, https://github.com/Jonas1015/chacc-dependency-manager/blob/main/README.md
Project-URL: Issues, https://github.com/Jonas1015/chacc-dependency-manager/issues
Keywords: dependency,resolution,pip,packaging,cache,requirements
Classifier: Development Status :: 4 - Beta
Classifier: Intended Audience :: Developers
Classifier: License :: OSI Approved :: MIT License
Classifier: Operating System :: OS Independent
Classifier: Programming Language :: Python :: 3
Classifier: Programming Language :: Python :: 3.8
Classifier: Programming Language :: Python :: 3.9
Classifier: Programming Language :: Python :: 3.10
Classifier: Programming Language :: Python :: 3.11
Classifier: Programming Language :: Python :: 3.12
Classifier: Topic :: Software Development :: Libraries :: Python Modules
Classifier: Topic :: System :: Software Distribution
Classifier: Topic :: Software Development :: Build Tools
Classifier: Topic :: System :: Archiving :: Packaging
Requires-Python: >=3.8
License-File: LICENSE
Requires-Dist: pip-tools>=7.0.0
Provides-Extra: full
Requires-Dist: pip-tools>=7.0.0; extra == "full"
Requires-Dist: pytest>=7.0.0; extra == "full"
Requires-Dist: pytest-asyncio>=0.21.0; extra == "full"
Requires-Dist: black>=22.0.0; extra == "full"
Requires-Dist: flake8>=4.0.0; extra == "full"
Requires-Dist: mypy>=1.0.0; extra == "full"
Requires-Dist: twine>=4.0.0; extra == "full"
Requires-Dist: build>=1.0.0; extra == "full"
Provides-Extra: resolver
Requires-Dist: pip-tools>=7.0.0; extra == "resolver"
Provides-Extra: dev
Requires-Dist: pytest>=7.0.0; extra == "dev"
Requires-Dist: pytest-asyncio>=0.21.0; extra == "dev"
Requires-Dist: black>=22.0.0; extra == "dev"
Requires-Dist: flake8>=4.0.0; extra == "dev"
Requires-Dist: mypy>=1.0.0; extra == "dev"
Requires-Dist: twine>=4.0.0; extra == "dev"
Requires-Dist: build>=1.0.0; extra == "dev"
Provides-Extra: test
Requires-Dist: pytest>=7.0.0; extra == "test"
Requires-Dist: pytest-asyncio>=0.21.0; extra == "test"
Provides-Extra: lint
Requires-Dist: black>=22.0.0; extra == "lint"
Requires-Dist: flake8>=4.0.0; extra == "lint"
Requires-Dist: mypy>=1.0.0; extra == "lint"
Dynamic: license-file
